setup.py
datastore/__init__.py
datastore.redis.egg-info/PKG-INFO
datastore.redis.egg-info/SOURCES.txt
datastore.redis.egg-info/dependency_links.txt
datastore.redis.egg-info/namespace_packages.txt
datastore.redis.egg-info/requires.txt
datastore.redis.egg-info/top_level.txt
datastore/redis/__init__.py
datastore/redis/test.py