Metadata-Version: 1.0
Name: datastore.redis
Version: 0.1.3
Summary: redis datastore implementation
Home-page: http://github.com/datastore/datastore.redis
Author: Juan Batiz-Benet
Author-email: juan@benet.ai
License: MIT License
Keywords: datastore,redis
Platform: UNKNOWN
Classifier: Topic :: Database
Classifier: Topic :: Database :: Front-Ends
